setup.py
zabbix_powerline_status.egg-info/PKG-INFO
zabbix_powerline_status.egg-info/SOURCES.txt
zabbix_powerline_status.egg-info/dependency_links.txt
zabbix_powerline_status.egg-info/requires.txt
zabbix_powerline_status.egg-info/top_level.txt
zabbix_segment/__init__.py
zabbix_segment/segment.py