Metadata-Version: 1.1
Name: zabbix-powerline-status
Version: 0.0.2
Summary: Zabbix powerline extension to show current triggers
Home-page: http://bitbucket.org/colinbits/zabbix-powerline-status
Author: Colin Wood
Author-email: cwood06@gmail.com
License: UNKNOWN
Download-URL: http://bitbucket.org/colinbits/zabbix-powerline-status
Platform: UNKNOWN
